xmas_app/components/__init__.py
xmas_app/components/association.py
xmas_app/components/buttons.py
xmas_app/components/label.py
xmas_app/db.py
xmas_app/db_uow.py
xmas_app/deps/version_guard.py
xmas_app/form.py
xmas_app/main.py
xmas_app/models/crud.py
xmas_app/models/mappings.py
xmas_app/pygeoapi/config.yaml
xmas_app/pygeoapi/openapi.yaml
xmas_app/pygeoapi/provider.py
xmas_app/resources/mappings.toml
xmas_app/schema.py
xmas_app/services/crud.py
xmas_app/settings.py
xmas_app/split_service.py
xmas_app/util/__init__.py
xmas_app/util/codelist.py
xmas_app-0.14.0.dist-info/METADATA
xmas_app-0.14.0.dist-info/WHEEL
xmas_app-0.14.0.dist-info/entry_points.txt
xmas_app-0.14.0.dist-info/licenses/LICENSE
xmas_app-0.14.0.dist-info/RECORD
