Metadata-Version: 2.4
Name: xmas-app
Version: 0.14.0
Summary: The XLeitstelle model-driven application schema app.
License: EUPL-1.2-or-later
License-File: LICENSE
Author: Tobias Kraft
Author-email: tobias.kraft@gv.hamburg.de
Requires-Python: >=3.11,<3.14
Classifier: Development Status :: 4 - Beta
Classifier: Framework :: Pydantic :: 2
Classifier: License :: OSI Approved :: European Union Public Licence 1.2 (EUPL 1.2)
Classifier: Operating System :: OS Independent
Classifier: Programming Language :: Python :: 3
Requires-Dist: nicegui (>=2.20,<3.0)
Requires-Dist: pydantic-extra-types[semver]
Requires-Dist: pydantic-settings (>=2.0,<3.0)
Requires-Dist: xplan-tools (>=1.12.1,<1.13.0)
Project-URL: Homepage, https://gitlab.opencode.de/xleitstelle/xmas-app
Project-URL: Issues, https://gitlab.opencode.de/xleitstelle/xmas-app/-/issues
